ezscrape/__init__.py
ezscrape/project_logger.py
ezscrape/scraping/__init__.py
ezscrape/scraping/core.py
ezscrape/scraping/exceptions.py
ezscrape/scraping/scraper.py
ezscrape/scraping/scraper_requests.py
ezscrape/scraping/scraper_selenium.py
ezscrape/scraping/web_lib.py
ezscrape-0.4.dist-info/LICENSE
ezscrape-0.4.dist-info/METADATA
ezscrape-0.4.dist-info/WHEEL
ezscrape-0.4.dist-info/top_level.txt
ezscrape-0.4.dist-info/RECORD
